kodey/__init__.py
kodey-0.1.0.dist-info/METADATA
kodey-0.1.0.dist-info/WHEEL
kodey-0.1.0.dist-info/RECORD
