Metadata-Version: 2.1
Name: kodey
Version: 0.1.0
Summary: Coming soon.
License: MIT
Author: Rob
Author-email: robert.i.hendry@gmail.com
Requires-Python: >=3.11,<4.0
Classifier: License :: OSI Approved :: MIT License
Classifier: Programming Language :: Python :: 3
Classifier: Programming Language :: Python :: 3.11
Classifier: Programming Language :: Python :: 3.12
